[{"date":"20.06.2025. 10:30","end":"Karlovac","id":1,"start":"Zagreb","status":"NOVO","userId":1},{"date":"25.06.2025. 08:00","end":"Varaždin","id":2,"start":"Zagreb","status":"NOVO","userId":1},{"date":"18.06.2025. 14:00","end":"Trogir","id":3,"start":"Split","status":"NOVO","userId":2},{"date":"17.06.2025. 09:15","end":"Opatija","id":4,"start":"Rijeka","status":"NOVO","userId":3},{"date":"15.06.2025. 18:45","end":"Sesvete","id":5,"start":"Zagreb","status":"STARO","userId":4},{"date":"22.06.2025. 11:00","end":"Vukovar","id":6,"start":"Osijek","status":"NOVO","userId":5},{"date":"19.06.2025. 16:30","end":"Biograd","id":7,"start":"Zadar","status":"NOVO","userId":6},{"date":"23.06.2025. 07:45","end":"Čakovec","id":8,"start":"Varaždin","status":"NOVO","userId":7},{"date":"21.06.2025. 19:00","end":"Omiš","id":9,"start":"Split","status":"NOVO","userId":2},{"date":"26.06.2025. 12:00","end":"Crikvenica","id":10,"start":"Rijeka","status":"NOVO","userId":3},{"date":"2026-01-22","end":"zagreb","id":0,"start":"zabok","userId":90},{"date":"2026-01-30","end":"rij","id":0,"start":"zag","userId":90},{"date":"2026-01-29","end":"rij","id":0,"start":"zag","userId":90},{"date":"2026-01-31","end":"zadar","id":0,"start":"rijeka","userId":90},{"date":"2026-01-28","end":"dubrovnik","id":0,"start":"osijek","userId":90}]